ImgWebp/__init__.py
ImgWebp/__main__.py
ImgWebp/console/__init__.py
ImgWebp/console/application.py
ImgWebp/console/command_loader.py
ImgWebp/console/command_ui.py
ImgWebp/console/commands/command.py
ImgWebp/console/commands/cwebp.py
ImgWebp/console/commands/download.py
ImgWebp/console/commands/dwebp.py
ImgWebp/console/commands/gif2webp.py
ImgWebp/console/commands/img2webp.py
ImgWebp/console/commands/version.py
ImgWebp/console/exceptions.py
ImgWebp/utils/CustomPath.py
ImgWebp/utils/__init__.py
ImgWebp/utils/download_libwebp.py
ImgWebp/utils/log.py
ImgWebp/utils/path.py
ImgWebp/utils/script.py
ImgWebp/utils/style.qss
imgwebp-0.3.2.dist-info/METADATA
imgwebp-0.3.2.dist-info/WHEEL
imgwebp-0.3.2.dist-info/entry_points.txt
imgwebp-0.3.2.dist-info/RECORD
